adder/adder.v
`timescale 1ns / 1ps

module mpadder(
    input  wire          clk,
    input  wire          resetn,
    input  wire          start,
    input  wire          subtract,
    input  wire [1026:0] in_a,
    input  wire [1026:0] in_b,
    output reg  [1027:0] result,
    output wire          done    
    );
        reg [1:0] state, nextstate;

    // Definition register A
    reg          regA_en;
    wire [1026:0] regA_D;// in
    reg  [1026:0] regA_Q;// out
    always @(posedge clk)
    begin
        if(~resetn || state == 1'd0)         regA_Q = 1027'd0;
        else if (regA_en)   regA_Q <= regA_D;
    end
    // Definition register B 
    reg          regB_en;   
    wire [1026:0] regB_D;   // in
    reg  [1026:0] regB_Q;   // out
    always @(posedge clk)
    begin
        if(~resetn || state == 1'd0)         regB_Q = 1027'd0;
        else if (regB_en) begin
           regB_Q <= regB_D;
           
        end
    end
    
    //Multiplexer for A
    reg          muxA_sel;
    reg  [1026:0] muxA_Out;
    always@(posedge clk) begin
        if (muxA_sel==1'b0) muxA_Out <= in_a;
        else                muxA_Out <= muxA_Out >> 64;
    end

    assign regA_D = muxA_Out;
    
    
    //Multiplexer for B
    reg          muxB_sel;
    reg  [1026:0] muxB_Out;
    always@(posedge clk) begin
        if (muxB_sel==1'b0) muxB_Out <= in_b;
        else                muxB_Out <= muxB_Out >> 64;
    end

    assign regB_D = muxB_Out;
    
    //64-bit adder
    wire [63:0] operandA;
    wire [63:0] operandB;
    wire        carry_in;
    wire [63:0] resultadd;
    wire        carry_out;
     reg [4:0] count;
    
    // keeps running maybe not the wisest thing to do
    assign {carry_out,resultadd} = operandA + operandB + carry_in;
    
    //storing result adder in 1027-bit register
    
    reg          regResult_en;
    reg  [1087:0] regResult;
    always @(posedge clk)
    begin
        if(~resetn)             regResult <= 1088'b0;
        else if (regResult_en) begin  
                        regResult = regResult >> 64;
                        regResult = {resultadd, regResult[1023:0]};
                        //regResult <= {resultadd, regResult[1023:0] >> 64};
                        // when ran as a non blocking statement we observe unexpected behavior
        end
    end
    
    //DBG
    //wire [63:0] dbg;
    //assign dbg = result[63:0];
    //    wire [63:0] dbg_2;
    //assign dbg_2 = result[127:64];
    //    wire [63:0] dbg_a;
    //assign dbg_a = in_a[63:0];
    //    wire [63:0] dbg_b;
    //assign dbg_b = in_b[63:0];
    
    //Storing carry in 1-bit register
    
    reg  regCout_en;
    reg  regCout;
    reg state_start;
    reg state_compute;


    
        always @(posedge clk)
            begin
                if(~resetn || (state==2'd2))          
                    regCout <= 1'b0;
                else if (regCout_en)  //
                    regCout <= carry_out;
                else
                    regCout <= 1'b0; // to clean ? 
                 
        end
                
     //Multiplexer that supplies the carry after each addition
     reg  muxCarryIn_sel;
     wire muxCarryIn;
    
     assign muxCarryIn = (muxCarryIn_sel == 0) ? 1'b0 : (subtract ? regCout : regCout);
     
     // Connecting outputs first registers to adder inputs
     assign operandA = regA_Q;
     assign operandB = subtract ? (count == 5'd1 ? ~regB_Q[63:0] + 64'd1 : ~regB_Q[63:0] ) : regB_Q[63:0]; // disgusting but works (???)
     assign carry_in = muxCarryIn;
     
     // Connecting output registers to one output
     always@(*)
     begin
        result <= regResult[1027:0];
     end
     
     //State Machine shifting

    always @(posedge clk)
    begin
        if(~resetn)	state <= 2'd0;
        else        state <= nextstate;
    end
     //Output of carry_out + result assigned to
    //     assign  = 
    always @(*) begin
         case(state)
         
         // waiting stage
            2'd0: begin
                regA_en          <= 1'b1;
                regB_en          <= 1'b1;
                regResult_en     <= 1'b0;
                regCout_en       <= 1'b0;
                muxCarryIn_sel   <= 1'b0;
                muxA_sel         <= 1'b0;  // Select in_a for shifting
                muxB_sel         <= 1'b0;  // Select in_b for shifting
            end
            
            // shifting stage;
            2'd1: begin
                regA_en        <= 1'b1;
                regB_en        <= 1'b1;
                regResult_en   <= 1'b1;
                regCout_en     <= 1'b1;
                muxCarryIn_sel <= 1'b1;
                muxA_sel       <= 1'b1;  // Select in_a for shifting
                muxB_sel       <= 1'b1;  // Select in_b for shifting
            end
            
            2'd2: begin
                regA_en        <= 1'b0;
                regB_en        <= 1'b0;
                regResult_en   <= 1'b0;
                regCout_en     <= 1'b0;
                muxCarryIn_sel <= 1'b1;
                muxA_sel        <= 1'b0;  // Select in_a for shifting
                muxB_sel        <= 1'b0;  // Select in_b for shifting
            end

            default: begin
                regA_en        <= 1'b0;
                regB_en        <= 1'b0;
                regResult_en   <= 1'b1;
                regCout_en     <= 1'b0;
                muxCarryIn_sel <= 1'b0;
                muxA_sel       <= 1'b0;  // Select in_a for shifting
                muxB_sel       <= 1'b0;  // Select in_b for shifting
            end
        endcase
    end
    
    always @(posedge clk)
    begin
        if(state==2'd1) begin
        count <= count + 1;
        end else begin
        count <= 5'd0;
        end
    end
        
    always @(*)
    begin
        case(state)
            2'd0   : begin
                if(start) begin
                    nextstate <= 2'd1;
                    
                end else begin
                    nextstate <= 2'd0;
                    end
            end

            2'd1   : begin
            
                if(count >= 5'd16) begin // will repeat 16 times in the loop state 1 and last one in state 2
                    nextstate <= 2'd2;
                 end else begin
                    nextstate <= 2'd1;
                 end
         end
         
            2'd2   : begin
               nextstate <= 2'd0;
            end
            
            default: begin
            nextstate <= 2'd0; 
            end
        endcase
    end
    
    reg delayRegDone;
    reg regDone;
    always @(posedge clk)
    begin
        if(~resetn) delayRegDone <= 1'b0;
        else        delayRegDone <= (state==2'd2) ? 1'b1 : 1'b0;
    end

    always @(posedge clk)
    begin 
        if(~resetn) regDone <= 1'b0;
        else        regDone <= delayRegDone;
    end

    assign done = regDone;

endmodule

adder/adder_tb.v
`timescale 1ns / 1ps
`include "adder.v"

module tb_mpadder;

    // Inputs
    reg clk;
    reg resetn;
    reg start;
    reg subtract;
    reg [1026:0] in_a;
    reg [1026:0] in_b;

    // Outputs
    wire [1027:0] result;
    wire done;

    // Test values
    reg [1027:0] expected_results;

    // Instantiate the mpadder module
    mpadder uut (
        .clk(clk),
        .resetn(resetn),
        .start(start),
        .subtract(subtract),
        .in_a(in_a),
        .in_b(in_b),
        .result(result),
        .done(done)
    );

    // Generate clock signal with a period of 10 time units (100 MHz frequency)
    always #5 clk = ~clk;

    // Test sequence
    initial begin
        // Initialize inputs
        clk = 0;
        resetn = 0;
        start = 0;
        subtract = 0;
        in_a = 0;
        in_b = 0;

        // Dump waveforms for analysis
        $dumpfile("mpadder.vcd");
        $dumpvars(0, tb_mpadder);

        // Apply reset
        #10 resetn = 1;

        // Test Case 1: Simple addition of two numbers
        #10 start = 1;
            in_a = 1027'd1000;
            in_b = 1027'd2000;
            subtract = 0; // Addition
            expected_results = 1028'd3000;
        #10 start = 0; // Deassert start signal

        // Wait for 'done' signal to go high
        wait (done);
        #10;

        // Test Case 2: Simple subtraction of two numbers
        #10 start = 1;
            in_a = 1027'd3000;
            in_b = 1027'd1500;
            subtract = 1; // Subtraction
            expected_results = 1028'd1500;
        #10 start = 0; // Deassert start signal

        // Wait for 'done' signal to go high
        wait (done);
        $display("Diff =%x", expected_results-result);

        #10;

        // Test Case 3: Edge case - large numbers addition
        #10 start = 1;
            in_a = 1027'h5037a57ca996db568fd681b0eee5660d8b1bac3f26d4c7d4bfd7569cea79a145a1e92496b29b0ef27b1f1138ef99808032375ae31820c93afee07f59b71f0e9205b2df5de5917242015ab0523b77d8245cab5c51b0ecfd3a04343fefd3da2e2f847a2628d9042682c37ea70249c53f1044691d3d8640223354bab205a3d87c0c5; // Maximum 1026-bit value
            in_b = 1027'h57094adfb92250358e5b00f6b91f711ce3d00dcd6651b2d9e99f080272a4067278e091cd48a8afc8c898f3a6c438ad9c940c8783c45054fde3c9926381f52222525b425eab03e92e43ef615df37a8b6cde00524ff913662ac768b37a8361c968d9304f920b7f1f278daabc7fa237c56112df9aeab7534a3f5fd7163600e67b0a9; // Slightly smaller max value
            expected_results = 1028'ha740f05c62b92b8c1e3182a7a804d72a6eebba0c8d267aaea9765e9f5d1da7b81ac9b663fb43bebb43b804dfb3d22e1cc643e266dc711e38e2aa11bd391430b4580e21bc90955b70454a11b02ef263913aabaea1aa006364cb9cf36a573bf7985daa75bae48345aa51296381ebfd04715748b8283d936c72b491c83ba4bef716e;
            subtract = 0; // Addition
        #10 start = 0; // Deassert start signal

        // Wait for 'done' signal to go high
        wait (done);
        #10;

        // Test Case 4: Edge case - large numbers subtraction
        #10 start = 1;
            in_a = 1027'h6a26b6195145db76f720b63f19f8844a6a3e6801ff7bd0d62949563cce5ea2f66e14a3c862d706bd44db1b6ea65e84b5ea9f958955a8a2fcb397a1a11f2ac168eb388d8ab437bcca0fce5d8a5e16cb726bfe06c35ec0631672102a495598b6a803d04a2d67351297accdbdec0e46d3c4784d46f3d20832d050d5b65d5cb0474e4; // Maximum 1026-bit value
            in_b = 1027'h4e5d2a0b6da45e13044a6596d0b5200547e40e18abb2eff5d07226cb694813af04d61b44d0e18de8220298844f81a262378d23c4c1849106db5fb6ffd82a90622b33f832a740c3929f2cc8eb7aef7de89c6f982179ef0d1d28338d61e056df1f51cb4e811c6e6a5b90e7078e5e89aade568659c2d327c79488b57eb53575398a8; // Slightly smaller max value
            subtract = 1; // Subtraction
            expected_results = 1028'h1bc98c0de3a17d63f2d650a849436445225a59e953c8e0e058d72f7165168f47693e888391f578d522d882ea56dce253b31271c4942411f5d837eaa147003106c00495580cf6f93770a1949ee3274d89cf8e6ea1e4d155f949dc9ce77541d788b204fbac4ac6a83c1be6b65dafbd28e621c6ed30fee06b3bc82037a8273b0dc3c;
        #10 start = 0; // Deassert start signal

        // Wait for 'done' signal to go high
        wait (done);
        $display("Diff =%x", expected_results-result);

        #10;

        // Finish simulation
        $finish;
    end

endmodule

adder/mpadder.vcd
$date
	Mon Nov  4 21:03:06 2024
$end
$version
	Icarus Verilog
$end
$timescale
	1ps
$end
$scope module tb_mpadder $end
$var wire 1028 ! result [1027:0] $end
$var wire 1 " done $end
$var reg 1 # clk $end
$var reg 1028 $ expected_results [1027:0] $end
$var reg 1027 % in_a [1026:0] $end
$var reg 1027 & in_b [1026:0] $end
$var reg 1 ' resetn $end
$var reg 1 ( start $end
$var reg 1 ) subtract $end
$scope module uut $end
$var wire 1 * carry_in $end
$var wire 1 # clk $end
$var wire 1 " done $end
$var wire 1027 + in_a [1026:0] $end
$var wire 1027 , in_b [1026:0] $end
$var wire 1027 - regA_D [1026:0] $end
$var wire 1027 . regB_D [1026:0] $end
$var wire 1 ' resetn $end
$var wire 1 ( start $end
$var wire 1 ) subtract $end
$var wire 64 / resultadd [63:0] $end
$var wire 64 0 operandB [63:0] $end
$var wire 64 1 operandA [63:0] $end
$var wire 1 2 muxCarryIn $end
$var wire 1 3 carry_out $end
$var reg 5 4 count [4:0] $end
$var reg 1 5 delayRegDone $end
$var reg 1027 6 muxA_Out [1026:0] $end
$var reg 1 7 muxA_sel $end
$var reg 1027 8 muxB_Out [1026:0] $end
$var reg 1 9 muxB_sel $end
$var reg 1 : muxCarryIn_sel $end
$var reg 2 ; nextstate [1:0] $end
$var reg 1027 < regA_Q [1026:0] $end
$var reg 1 = regA_en $end
$var reg 1027 > regB_Q [1026:0] $end
$var reg 1 ? regB_en $end
$var reg 1 @ regCout $end
$var reg 1 A regCout_en $end
$var reg 1 B regDone $end
$var reg 1088 C regResult [1087:0] $end
$var reg 1 D regResult_en $end
$var reg 1028 E result [1027:0] $end
$var reg 2 F state [1:0] $end
$upscope $end
$upscope $end
$enddefinitions $end
$comment Show the parameter values. $end
$dumpall
$end
#0
$dumpvars
bx F
bx E
xD
bx C
xB
xA
x@
x?
bx >
x=
bx <
b0 ;
x:
x9
bx 8
x7
bx 6
x5
bx 4
x3
x2
bx 1
bx 0
bx /
bx .
bx -
b0 ,
b0 +
x*
0)
0(
0'
b0 &
b0 %
bx $
0#
x"
bx !
$end
#5000
b0 !
b0 E
09
07
0:
0A
0D
1?
1=
b0 /
03
0*
02
b0xxxxxxxxxxxxxxxxxxxxxxxxxxxxxxxxxxxxxxxxxxxxxxxxxxxxxxxxxxxxxxxxxxxxxxxxxxxxxxxxxxxxxxxxxxxxxxxxxxxxxxxxxxxxxxxxxxxxxxxxxxxxxxxxxxxxxxxxxxxxxxxxxxxxxxxxxxxxxxxxxxxxxxxxxxxxxxxxxxxxxxxxxxxxxxxxxxxxxxxxxxxxxxxxxxxxxxxxxxxxxxxxxxxxxxxxxxxxxxxxxxxxxxxxxxxxxxxxxxxxxxxxxxxxxxxxxxxxxxxxxxxxxxxxxxxxxxxxxxxxxxxxxxxxxxxxxxxxxxxxxxxxxxxxxxxxxxxxxxxxxxxxxxxxxxxxxxxxxxxxxxxxxxxxxxxxxxxxxxxxxxxxxxxxxxxxxxxxxxxxxxxxxxxxxxxxxxxxxxxxxxxxxxxxxxxxxxxxxxxxxxxxxxxxxxxxxxxxxxxxxxxxxxxxxxxxxxxxxxxxxxxxxxxxxxxxxxxxxxxxxxxxxxxxxxxxxxxxxxxxxxxxxxxxxxxxxxxxxxxxxxxxxxxxxxxxxxxxxxxxxxxxxxxxxxxxxxxxxxxxxxxxxxxxxxxxxxxxxxxxxxxxxxxxxxxxxxxxxxxxxxxxxxxxxxxxxxxxxxxxxxxxxxxxxxxxxxxxxxxxxxxxxxxxxxxxxxxxxxxxxxxxxxxxxxxxxxxxxxxxxxxxxxxxxxxxxxxxxxxxxxxxxxxxxxxxxxxxxxxxxxxxxxxxxxxxxxxxxxxxxxxxxxxxxxxxxxxxxxxxxxxxxxxxxxxxxxxxxxxxxxxxxxxxxxxxxxxxxxxxxxxxxxxxxxxxxxxxxxxxxxxxxxxxxxxxxxxxxxxxxxxxxxxxxxxxxxxxxxxxxxxxxxxxxxxxxxxxxxxxxxxxxxxxxxxxxxxxxxxxxxxxxxxxxxxxxxxxxxxxxxxxxxxxxxxxxxxxxxxxxxx -
b0xxxxxxxxxxxxxxxxxxxxxxxxxxxxxxxxxxxxxxxxxxxxxxxxxxxxxxxxxxxxxxxxxxxxxxxxxxxxxxxxxxxxxxxxxxxxxxxxxxxxxxxxxxxxxxxxxxxxxxxxxxxxxxxxxxxxxxxxxxxxxxxxxxxxxxxxxxxxxxxxxxxxxxxxxxxxxxxxxxxxxxxxxxxxxxxxxxxxxxxxxxxxxxxxxxxxxxxxxxxxxxxxxxxxxxxxxxxxxxxxxxxxxxxxxxxxxxxxxxxxxxxxxxxxxxxxxxxxxxxxxxxxxxxxxxxxxxxxxxxxxxxxxxxxxxxxxxxxxxxxxxxxxxxxxxxxxxxxxxxxxxxxxxxxxxxxxxxxxxxxxxxxxxxxxxxxxxxxxxxxxxxxxxxxxxxxxxxxxxxxxxxxxxxxxxxxxxxxxxxxxxxxxxxxxxxxxxxxxxxxxxxxxxxxxxxxxxxxxxxxxxxxxxxxxxxxxxxxxxxxxxxxxxxxxxxxxxxxxxxxxxxxxxxxxxxxxxxxxxxxxxxxxxxxxxxxxxxxxxxxxxxxxxxxxxxxxxxxxxxxxxxxxxxxxxxxxxxxxxxxxxxxxxxxxxxxxxxxxxxxxxxxxxxxxxxxxxxxxxxxxxxxxxxxxxxxxxxxxxxxxxxxxxxxxxxxxxxxxxxxxxxxxxxxxxxxxxxxxxxxxxxxxxxxxxxxxxxxxxxxxxxxxxxxxxxxxxxxxxxxxxxxxxxxxxxxxxxxxxxxxxxxxxxxxxxxxxxxxxxxxxxxxxxxxxxxxxxxxxxxxxxxxxxxxxxxxxxxxxxxxxxxxxxxxxxxxxxxxxxxxxxxxxxxxxxxxxxxxxxxxxxxxxxxxxxxxxxxxxxxxxxxxxxxxxxxxxxxxxxxxxxxxxxxxxxxxxxxxxxxxxxxxxxxxxxxxxxxxxxxxxxxxxxxxxxxxxxxxxxxxxxxxxxxxxxxxxxxxxxxxxx 6
b0xxxxxxxxxxxxxxxxxxxxxxxxxxxxxxxxxxxxxxxxxxxxxxxxxxxxxxxxxxxxxxxxxxxxxxxxxxxxxxxxxxxxxxxxxxxxxxxxxxxxxxxxxxxxxxxxxxxxxxxxxxxxxxxxxxxxxxxxxxxxxxxxxxxxxxxxxxxxxxxxxxxxxxxxxxxxxxxxxxxxxxxxxxxxxxxxxxxxxxxxxxxxxxxxxxxxxxxxxxxxxxxxxxxxxxxxxxxxxxxxxxxxxxxxxxxxxxxxxxxxxxxxxxxxxxxxxxxxxxxxxxxxxxxxxxxxxxxxxxxxxxxxxxxxxxxxxxxxxxxxxxxxxxxxxxxxxxxxxxxxxxxxxxxxxxxxxxxxxxxxxxxxxxxxxxxxxxxxxxxxxxxxxxxxxxxxxxxxxxxxxxxxxxxxxxxxxxxxxxxxxxxxxxxxxxxxxxxxxxxxxxxxxxxxxxxxxxxxxxxxxxxxxxxxxxxxxxxxxxxxxxxxxxxxxxxxxxxxxxxxxxxxxxxxxxxxxxxxxxxxxxxxxxxxxxxxxxxxxxxxxxxxxxxxxxxxxxxxxxxxxxxxxxxxxxxxxxxxxxxxxxxxxxxxxxxxxxxxxxxxxxxxxxxxxxxxxxxxxxxxxxxxxxxxxxxxxxxxxxxxxxxxxxxxxxxxxxxxxxxxxxxxxxxxxxxxxxxxxxxxxxxxxxxxxxxxxxxxxxxxxxxxxxxxxxxxxxxxxxxxxxxxxxxxxxxxxxxxxxxxxxxxxxxxxxxxxxxxxxxxxxxxxxxxxxxxxxxxxxxxxxxxxxxxxxxxxxxxxxxxxxxxxxxxxxxxxxxxxxxxxxxxxxxxxxxxxxxxxxxxxxxxxxxxxxxxxxxxxxxxxxxxxxxxxxxxxxxxxxxxxxxxxxxxxxxxxxxxxxxxxxxxxxxxxxxxxxxxxxxxxxxxxxxxxxxxxxxxxxxxxxxxxxxxxxxxxxxxxxxxxxx .
b0xxxxxxxxxxxxxxxxxxxxxxxxxxxxxxxxxxxxxxxxxxxxxxxxxxxxxxxxxxxxxxxxxxxxxxxxxxxxxxxxxxxxxxxxxxxxxxxxxxxxxxxxxxxxxxxxxxxxxxxxxxxxxxxxxxxxxxxxxxxxxxxxxxxxxxxxxxxxxxxxxxxxxxxxxxxxxxxxxxxxxxxxxxxxxxxxxxxxxxxxxxxxxxxxxxxxxxxxxxxxxxxxxxxxxxxxxxxxxxxxxxxxxxxxxxxxxxxxxxxxxxxxxxxxxxxxxxxxxxxxxxxxxxxxxxxxxxxxxxxxxxxxxxxxxxxxxxxxxxxxxxxxxxxxxxxxxxxxxxxxxxxxxxxxxxxxxxxxxxxxxxxxxxxxxxxxxxxxxxxxxxxxxxxxxxxxxxxxxxxxxxxxxxxxxxxxxxxxxxxxxxxxxxxxxxxxxxxxxxxxxxxxxxxxxxxxxxxxxxxxxxxxxxxxxxxxxxxxxxxxxxxxxxxxxxxxxxxxxxxxxxxxxxxxxxxxxxxxxxxxxxxxxxxxxxxxxxxxxxxxxxxxxxxxxxxxxxxxxxxxxxxxxxxxxxxxxxxxxxxxxxxxxxxxxxxxxxxxxxxxxxxxxxxxxxxxxxxxxxxxxxxxxxxxxxxxxxxxxxxxxxxxxxxxxxxxxxxxxxxxxxxxxxxxxxxxxxxxxxxxxxxxxxxxxxxxxxxxxxxxxxxxxxxxxxxxxxxxxxxxxxxxxxxxxxxxxxxxxxxxxxxxxxxxxxxxxxxxxxxxxxxxxxxxxxxxxxxxxxxxxxxxxxxxxxxxxxxxxxxxxxxxxxxxxxxxxxxxxxxxxxxxxxxxxxxxxxxxxxxxxxxxxxxxxxxxxxxxxxxxxxxxxxxxxxxxxxxxxxxxxxxxxxxxxxxxxxxxxxxxxxxxxxxxxxxxxxxxxxxxxxxxxxxxxxxxxxxxxxxxxxxxxxxxxxxxxxxxxxxxxxx 8
b0 C
0@
b0 F
b0 4
05
0"
0B
b0 0
b0 1
b0 <
b0 >
1#
#10000
0#
1'
#15000
b0 .
b0 8
b0 -
b0 6
1#
#20000
b1 ;
0#
b101110111000 $
b11111010000 &
b11111010000 ,
b1111101000 %
b1111101000 +
1(
#25000
19
17
1:
1A
1D
b1111101000 -
b1111101000 6
b11111010000 .
b11111010000 8
b1 F
1#
#30000
0#
0(
#35000
b11111010000 0
b101110111000 /
b1111101000 1
b1 4
b0 .
b0 8
b0 -
b0 6
b11111010000 >
b1111101000 <
1#
#40000
0#
#45000
b0 /
b0 0
b0 1
b10000000000000000000000000000000000000000000000000000000000000000000000000000000000000000000000000000000000000000000000000000000000000000000000000000000000000000000000000000000000000000000000000000000000000000000000000000000000000000000000000000000000000000000000000000000000000000000000000000000000000000000000000000000000000000000000000000000000000000000000000000000000000000000000000000000000000000000000000000000000000000000000000000000000000000000000000000000000000000000000000000000000000000000000000000000000000000000000000000000000000000000000000000000000000000000000000000000000000000000000000000000000000000000000000000000000000000000000000000000000000000000000000000000000000000000000000000000000000000000000000000000000000000000000000000000000000000000000000000000000000000000000000000000000000000000000000000000000000000000000000000000000000000000000000000000000000000000000000000000000000000000000000000000000000000000000000000000000000000000000000000000000000000000000000000000000000000000000000000000000000000000 !
b10000000000000000000000000000000000000000000000000000000000000000000000000000000000000000000000000000000000000000000000000000000000000000000000000000000000000000000000000000000000000000000000000000000000000000000000000000000000000000000000000000000000000000000000000000000000000000000000000000000000000000000000000000000000000000000000000000000000000000000000000000000000000000000000000000000000000000000000000000000000000000000000000000000000000000000000000000000000000000000000000000000000000000000000000000000000000000000000000000000000000000000000000000000000000000000000000000000000000000000000000000000000000000000000000000000000000000000000000000000000000000000000000000000000000000000000000000000000000000000000000000000000000000000000000000000000000000000000000000000000000000000000000000000000000000000000000000000000000000000000000000000000000000000000000000000000000000000000000000000000000000000000000000000000000000000000000000000000000000000000000000000000000000000000000000000000000000000000000000000000000000000 E
b0 <
b0 >
b10 4
b1011101110000000000000000000000000000000000000000000000000000000000000000000000000000000000000000000000000000000000000000000000000000000000000000000000000000000000000000000000000000000000000000000000000000000000000000000000000000000000000000000000000000000000000000000000000000000000000000000000000000000000000000000000000000000000000000000000000000000000000000000000000000000000000000000000000000000000000000000000000000000000000000000000000000000000000000000000000000000000000000000000000000000000000000000000000000000000000000000000000000000000000000000000000000000000000000000000000000000000000000000000000000000000000000000000000000000000000000000000000000000000000000000000000000000000000000000000000000000000000000000000000000000000000000000000000000000000000000000000000000000000000000000000000000000000000000000000000000000000000000000000000000000000000000000000000000000000000000000000000000000000000000000000000000000000000000000000000000000000000000000000000000000000000000000000000000000000000000000000000000000000000000000 C
1#
#50000
0#
#55000
b101110111000000000000000000000000000000000000000000000000000000000000000000000000000000000000000000000000000000000000000000000000000000000000000000000000000000000000000000000000000000000000000000000000000000000000000000000000000000000000000000000000000000000000000000000000000000000000000000000000000000000000000000000000000000000000000000000000000000000000000000000000000000000000000000000000000000000000000000000000000000000000000000000000000000000000000000000000000000000000000000000000000000000000000000000000000000000000000000000000000000000000000000000000000000000000000000000000000000000000000000000000000000000000000000000000000000000000000000000000000000000000000000000000000000000000000000000000000000000000000000000000000000000000000000000000000000000000000000000000000000000000000000000000000000000000000000000000000000000000000000000000000000000000000000000000000000000000000000000000000000000000000000000000000000000000000000000000000000000000000000000000000 !
b101110111000000000000000000000000000000000000000000000000000000000000000000000000000000000000000000000000000000000000000000000000000000000000000000000000000000000000000000000000000000000000000000000000000000000000000000000000000000000000000000000000000000000000000000000000000000000000000000000000000000000000000000000000000000000000000000000000000000000000000000000000000000000000000000000000000000000000000000000000000000000000000000000000000000000000000000000000000000000000000000000000000000000000000000000000000000000000000000000000000000000000000000000000000000000000000000000000000000000000000000000000000000000000000000000000000000000000000000000000000000000000000000000000000000000000000000000000000000000000000000000000000000000000000000000000000000000000000000000000000000000000000000000000000000000000000000000000000000000000000000000000000000000000000000000000000000000000000000000000000000000000000000000000000000000000000000000000000000000000000000000000000 E
b11 4
b101110111000000000000000000000000000000000000000000000000000000000000000000000000000000000000000000000000000000000000000000000000000000000000000000000000000000000000000000000000000000000000000000000000000000000000000000000000000000000000000000000000000000000000000000000000000000000000000000000000000000000000000000000000000000000000000000000000000000000000000000000000000000000000000000000000000000000000000000000000000000000000000000000000000000000000000000000000000000000000000000000000000000000000000000000000000000000000000000000000000000000000000000000000000000000000000000000000000000000000000000000000000000000000000000000000000000000000000000000000000000000000000000000000000000000000000000000000000000000000000000000000000000000000000000000000000000000000000000000000000000000000000000000000000000000000000000000000000000000000000000000000000000000000000000000000000000000000000000000000000000000000000000000000000000000000000000000000000000000000000000000000000 C
1#
#60000
0#
#65000
b10111011100000000000000000000000000000000000000000000000000000000000000000000000000000000000000000000000000000000000000000000000000000000000000000000000000000000000000000000000000000000000000000000000000000000000000000000000000000000000000000000000000000000000000000000000000000000000000000000000000000000000000000000000000000000000000000000000000000000000000000000000000000000000000000000000000000000000000000000000000000000000000000000000000000000000000000000000000000000000000000000000000000000000000000000000000000000000000000000000000000000000000000000000000000000000000000000000000000000000000000000000000000000000000000000000000000000000000000000000000000000000000000000000000000000000000000000000000000000000000000000000000000000000000000000000000000000000000000000000000000000000000000000000000000000000000000000000000000000000000000000000000000000000000000000000000000000000000000000000000000000000 !
b10111011100000000000000000000000000000000000000000000000000000000000000000000000000000000000000000000000000000000000000000000000000000000000000000000000000000000000000000000000000000000000000000000000000000000000000000000000000000000000000000000000000000000000000000000000000000000000000000000000000000000000000000000000000000000000000000000000000000000000000000000000000000000000000000000000000000000000000000000000000000000000000000000000000000000000000000000000000000000000000000000000000000000000000000000000000000000000000000000000000000000000000000000000000000000000000000000000000000000000000000000000000000000000000000000000000000000000000000000000000000000000000000000000000000000000000000000000000000000000000000000000000000000000000000000000000000000000000000000000000000000000000000000000000000000000000000000000000000000000000000000000000000000000000000000000000000000000000000000000000000000000 E
b100 4
b10111011100000000000000000000000000000000000000000000000000000000000000000000000000000000000000000000000000000000000000000000000000000000000000000000000000000000000000000000000000000000000000000000000000000000000000000000000000000000000000000000000000000000000000000000000000000000000000000000000000000000000000000000000000000000000000000000000000000000000000000000000000000000000000000000000000000000000000000000000000000000000000000000000000000000000000000000000000000000000000000000000000000000000000000000000000000000000000000000000000000000000000000000000000000000000000000000000000000000000000000000000000000000000000000000000000000000000000000000000000000000000000000000000000000000000000000000000000000000000000000000000000000000000000000000000000000000000000000000000000000000000000000000000000000000000000000000000000000000000000000000000000000000000000000000000000000000000000000000000000000000000 C
1#
#70000
0#
#75000
b1011101110000000000000000000000000000000000000000000000000000000000000000000000000000000000000000000000000000000000000000000000000000000000000000000000000000000000000000000000000000000000000000000000000000000000000000000000000000000000000000000000000000000000000000000000000000000000000000000000000000000000000000000000000000000000000000000000000000000000000000000000000000000000000000000000000000000000000000000000000000000000000000000000000000000000000000000000000000000000000000000000000000000000000000000000000000000000000000000000000000000000000000000000000000000000000000000000000000000000000000000000000000000000000000000000000000000000000000000000000000000000000000000000000000000000000000000000000000000000000000000000000000000000000000000000000000000000000000000000000000000000000000000000000000000000000000000000000000000000000000000 !
b1011101110000000000000000000000000000000000000000000000000000000000000000000000000000000000000000000000000000000000000000000000000000000000000000000000000000000000000000000000000000000000000000000000000000000000000000000000000000000000000000000000000000000000000000000000000000000000000000000000000000000000000000000000000000000000000000000000000000000000000000000000000000000000000000000000000000000000000000000000000000000000000000000000000000000000000000000000000000000000000000000000000000000000000000000000000000000000000000000000000000000000000000000000000000000000000000000000000000000000000000000000000000000000000000000000000000000000000000000000000000000000000000000000000000000000000000000000000000000000000000000000000000000000000000000000000000000000000000000000000000000000000000000000000000000000000000000000000000000000000000000 E
b101 4
b1011101110000000000000000000000000000000000000000000000000000000000000000000000000000000000000000000000000000000000000000000000000000000000000000000000000000000000000000000000000000000000000000000000000000000000000000000000000000000000000000000000000000000000000000000000000000000000000000000000000000000000000000000000000000000000000000000000000000000000000000000000000000000000000000000000000000000000000000000000000000000000000000000000000000000000000000000000000000000000000000000000000000000000000000000000000000000000000000000000000000000000000000000000000000000000000000000000000000000000000000000000000000000000000000000000000000000000000000000000000000000000000000000000000000000000000000000000000000000000000000000000000000000000000000000000000000000000000000000000000000000000000000000000000000000000000000000000000000000000000000000 C
1#
#80000
0#
#85000
b101110111000000000000000000000000000000000000000000000000000000000000000000000000000000000000000000000000000000000000000000000000000000000000000000000000000000000000000000000000000000000000000000000000000000000000000000000000000000000000000000000000000000000000000000000000000000000000000000000000000000000000000000000000000000000000000000000000000000000000000000000000000000000000000000000000000000000000000000000000000000000000000000000000000000000000000000000000000000000000000000000000000000000000000000000000000000000000000000000000000000000000000000000000000000000000000000000000000000000000000000000000000000000000000000000000000000000000000000000000000000000000000000000000000000000000000000000000000000000000000000000000000000000000000000000000000000000000000000000000000 !
b101110111000000000000000000000000000000000000000000000000000000000000000000000000000000000000000000000000000000000000000000000000000000000000000000000000000000000000000000000000000000000000000000000000000000000000000000000000000000000000000000000000000000000000000000000000000000000000000000000000000000000000000000000000000000000000000000000000000000000000000000000000000000000000000000000000000000000000000000000000000000000000000000000000000000000000000000000000000000000000000000000000000000000000000000000000000000000000000000000000000000000000000000000000000000000000000000000000000000000000000000000000000000000000000000000000000000000000000000000000000000000000000000000000000000000000000000000000000000000000000000000000000000000000000000000000000000000000000000000000000 E
b110 4
b101110111000000000000000000000000000000000000000000000000000000000000000000000000000000000000000000000000000000000000000000000000000000000000000000000000000000000000000000000000000000000000000000000000000000000000000000000000000000000000000000000000000000000000000000000000000000000000000000000000000000000000000000000000000000000000000000000000000000000000000000000000000000000000000000000000000000000000000000000000000000000000000000000000000000000000000000000000000000000000000000000000000000000000000000000000000000000000000000000000000000000000000000000000000000000000000000000000000000000000000000000000000000000000000000000000000000000000000000000000000000000000000000000000000000000000000000000000000000000000000000000000000000000000000000000000000000000000000000000000000 C
1#
#90000
0#
