adder/seven_multiplexer.v
module seven_multiplexer(
    input           clk,
    input           resetn,
    input [1026:0]  in_M,
    input [1026:0]  in_2M,
    input [1026:0]  in_3M,
    input [1026:0]  in_B,
    input [1026:0]  in_2B,
    input [1026:0]  in_3B,
    input [2:0]     select,
    output reg[1026:0] out
    );

    always @(posedge clk) begin
        if(~resetn)
            out <= 1027'd0;
        else begin
            case (select)
                3'b001 : out <= in_M; 
                3'b010 : out <= in_2M; 
                3'b011 : out <= in_3M; 
                3'b100 : out <= in_B; 
                3'b101 : out <= in_2B; 
                3'b110 : out <= in_3B; 
                default: out <= 1027'd0;
            endcase
        end
    end

endmodule

adder/seven_multiplexer_tb.v
`timescale 1ns / 1ps
`include "seven_multiplexer.v"

module tb_seven_multiplexer;

    // Testbench signals
    reg clk;
    reg resetn;
    reg [1026:0] in_M;
    reg [1026:0] in_2M;
    reg [1026:0] in_3M;
    reg [1026:0] in_B;
    reg [1026:0] in_2B;
    reg [1026:0] in_3B;
    reg [2:0] select;
    wire [1026:0] out;

    // Instantiate the design under test (DUT)
    seven_multiplexer uut (
        .clk(clk),
        .resetn(resetn),
        .in_M(in_M),
        .in_2M(in_2M),
        .in_3M(in_3M),
        .in_B(in_B),
        .in_2B(in_2B),
        .in_3B(in_3B),
        .select(select),
        .out(out)
    );

    // Clock generation
    always #5 clk = ~clk;  // 10ns clock period

    initial begin
        $dumpfile("tb_multi.vcd");
        $dumpvars(1, uut);

        // Initialize signals
        clk = 0;
        resetn = 0;
        select = 3'b000;
        in_M = 1027'd1;
        in_2M = 1027'd2;
        in_3M = 1027'd3;
        in_B = 1027'd4;
        in_2B = 1027'd5;
        in_3B = 1027'd6;

        // Apply reset
        #10 resetn = 1;  // Release reset after 10ns

        // Test different select values
        #10 select = 3'b001;  // Test in_M
        #10 select = 3'b010;  // Test in_2M
        #10 select = 3'b011;  // Test in_3M
        #10 select = 3'b100;  // Test in_B
        #10 select = 3'b101;  // Test in_2B
        #10 select = 3'b110;  // Test in_3B

        // Test default case
        #10 select = 3'b000;  // Expect out to be 0

        // End the simulation
        #20 $finish;
    end

    // Monitor output changes
    initial begin
        $monitor("Time=%0dns, select=%b, out=%d", $time, select, out);
    end

endmodule

adder/tb_multi.vcd
$date
	Sun Nov 03 12:08:26 2024
$end
$version
	Icarus Verilog
$end
$timescale
	1ps
$end
$scope module tb_seven_multiplexer $end
$scope module uut $end
$var wire 1 ! clk $end
$var wire 1027 " in_2B [1026:0] $end
$var wire 1027 # in_2M [1026:0] $end
$var wire 1027 $ in_3B [1026:0] $end
$var wire 1027 % in_3M [1026:0] $end
$var wire 1027 & in_B [1026:0] $end
$var wire 1027 ' in_M [1026:0] $end
$var wire 1 ( resetn $end
$var wire 3 ) select [2:0] $end
$var reg 1027 * out [1026:0] $end
$upscope $end
$upscope $end
$enddefinitions $end
#0
$dumpvars
bx *
b0 )
0(
b1 '
b100 &
b11 %
b110 $
b10 #
b101 "
0!
$end
#5000
b0 *
1!
#10000
0!
1(
#15000
1!
#20000
0!
b1 )
#25000
b1 *
1!
#30000
0!
b10 )
#35000
b10 *
1!
#40000
0!
b11 )
#45000
b11 *
1!
#50000
0!
b100 )
#55000
b100 *
1!
#60000
0!
b101 )
#65000
b101 *
1!
#70000
0!
b110 )
#75000
b110 *
1!
#80000
0!
b0 )
#85000
b0 *
1!
